README.md
setup.py
bnds_manager/__init__.py
bnds_manager/_hosts.py
bnds_manager/_version.py
bnds_manager/errors.py
bnds_manager/fields.py
bnds_manager/interface.py
bnds_manager/manager.py
bnds_manager/model.py
bnds_manager/nodes.py
bnds_manager/parsers.py
bnds_manager/tables.py
bnds_manager/widgets.py
bnds_manager.egg-info/PKG-INFO
bnds_manager.egg-info/SOURCES.txt
bnds_manager.egg-info/dependency_links.txt
bnds_manager.egg-info/requires.txt
bnds_manager.egg-info/top_level.txt