Metadata-Version: 2.4
Name: bnds_manager
Version: 0.7.2
Summary: Python API for managing models and configurations on the BNDS server
Home-page: https://github.research.its.qmul.ac.uk/deri-rim/bnds_manager
Author: Rachel Sumner
Author-email: r.sumner@qmul.ac.uk
Classifier: Programming Language :: Python :: 3
Classifier: License :: OSI Approved :: MIT License
Classifier: Operating System :: OS Independent
Requires-Dist: requests
Requires-Dist: simplejson
Requires-Dist: pandas
Requires-Dist: numpy
Dynamic: author
Dynamic: author-email
Dynamic: classifier
Dynamic: home-page
Dynamic: requires-dist
Dynamic: summary
